<net xmlns:xsi="http://www.w3.org/2001/XMLSchema-instance" version="1.9" junctionCornerDetail="5" limitTurnSpeed="5.50" xsi:noNamespaceSchemaLocation="http://sumo.dlr.de/xsd/net_file.xsd">

    <location netOffset="662.63,1134.68" convBoundary="0.00,0.00,1229.97,1747.28" origBoundary="-662.63,-1134.68,567.34,612.60" projParameter="!" />

    <edge id=":A_0" function="internal">
        <lane id=":A_0_0" index="0" speed="6.51" length="9.03" shape="664.23,1433.78,5.01 664.58,1436.23,5.04 665.63,1437.98,5.07 667.38,1439.03,5.10 669.83,1439.38,5.13" />
    </edge>
    <edge id=":A_1" function="internal">
        <lane id=":A_1_0" index="0" speed="11.18" length="14.40" shape="664.23,1433.78,5.01 664.23,1448.18,5.13" />
    </edge>
    <edge id=":A_2" function="internal">
        <lane id=":A_2_0" index="0" speed="7.33" length="11.73" shape="664.23,1433.78,5.01 663.88,1437.63,5.05 662.83,1440.38,5.08 661.08,1442.03,5.11 658.63,1442.58,5.13" />
    </edge>
    <edge id=":B_0" function="internal">
        <lane id=":B_0_0" index="0" speed="7.33" length="11.73" shape="828.72,1145.08,8.69 828.17,1142.63,8.69 826.52,1140.88,8.69 823.77,1139.83,8.69 819.92,1139.48,8.69" />
    </edge>
    <edge id=":B_1" function="internal">
        <lane id=":B_1_0" index="0" speed="13.41" length="24.00" shape="828.72,1145.08,8.69 828.72,1121.08,8.69" />
        <lane id=":B_1_1" index="1" speed="13.41" length="24.00" shape="831.92,1145.08,8.69 831.92,1121.08,8.69" />
    </edge>
    <edge id=":B_3" function="internal">
        <lane id=":B_3_0" index="0" speed="9.84" length="4.01" shape="831.92,1145.08,8.69 832.63,1141.13,8.69" />
    </edge>
    <edge id=":B_4" function="internal">
        <lane id=":B_4_0" index="0" speed="3.65" length="1.44" shape="831.92,1145.08,8.69 832.72,1143.88,8.69" />
    </edge>
    <edge id=":B_21" function="internal">
        <lane id=":B_21_0" index="0" speed="9.84" length="17.98" shape="832.63,1141.13,8.69 832.87,1139.83,8.69 835.72,1136.08,8.69 840.47,1133.83,8.69 847.12,1133.08,8.69" />
    </edge>
    <edge id=":B_22" function="internal">
        <lane id=":B_22_0" index="0" speed="3.65" length="3.23" shape="832.72,1143.88,8.69 833.52,1143.48,8.69 834.32,1143.88,8.69 835.12,1145.08,8.69" />
    </edge>
    <edge id=":B_5" function="internal">
        <lane id=":B_5_0" index="0" speed="6.51" length="9.03" shape="847.12,1139.48,8.69 844.67,1139.83,8.69 842.92,1140.88,8.69 841.87,1142.63,8.69 841.52,1145.08,8.69" />
    </edge>
    <edge id=":B_6" function="internal">
        <lane id=":B_6_0" index="0" speed="13.41" length="27.20" shape="847.12,1139.48,8.69 819.92,1139.48,8.69" />
        <lane id=":B_6_1" index="1" speed="13.41" length="27.20" shape="847.12,1136.28,8.69 819.92,1136.28,8.69" />
    </edge>
    <edge id=":B_8" function="internal">
        <lane id=":B_8_0" index="0" speed="10.36" length="5.01" shape="847.12,1136.28,8.69 842.15,1135.57,8.69" />
    </edge>
    <edge id=":B_9" function="internal">
        <lane id=":B_9_0" index="0" speed="3.65" length="1.44" shape="847.12,1136.28,8.69 845.92,1135.48,8.69" />
    </edge>
    <edge id=":B_23" function="internal">
        <lane id=":B_23_0" index="0" speed="10.36" length="19.50" shape="842.15,1135.57,8.69 840.47,1135.33,8.69 835.72,1132.48,8.69 832.87,1127.73,8.69 831.92,1121.08,8.69" />
    </edge>
    <edge id=":B_24" function="internal">
        <lane id=":B_24_0" index="0" speed="3.65" length="3.23" shape="845.92,1135.48,8.69 845.52,1134.68,8.69 845.92,1133.88,8.69 847.12,1133.08,8.69" />
    </edge>
    <edge id=":B_10" function="internal">
        <lane id=":B_10_0" index="0" speed="7.33" length="11.73" shape="838.32,1121.08,8.69 838.87,1123.53,8.69 840.52,1125.28,8.69 843.27,1126.33,8.69 847.12,1126.68,8.69" />
    </edge>
    <edge id=":B_11" function="internal">
        <lane id=":B_11_0" index="0" speed="13.41" length="24.00" shape="838.32,1121.08,8.69 838.32,1145.08,8.69" />
        <lane id=":B_11_1" index="1" speed="13.41" length="24.00" shape="835.12,1121.08,8.69 835.12,1145.08,8.69" />
    </edge>
    <edge id=":B_13" function="internal">
        <lane id=":B_13_0" index="0" speed="10.36" length="5.01" shape="835.12,1121.08,8.69 834.41,1126.04,8.69" />
    </edge>
    <edge id=":B_14" function="internal">
        <lane id=":B_14_0" index="0" speed="3.65" length="1.44" shape="835.12,1121.08,8.69 834.32,1122.28,8.69" />
    </edge>
    <edge id=":B_25" function="internal">
        <lane id=":B_25_0" index="0" speed="10.36" length="19.50" shape="834.41,1126.04,8.69 834.17,1127.73,8.69 831.32,1132.48,8.69 826.57,1135.33,8.69 819.92,1136.28,8.69" />
    </edge>
    <edge id=":B_26" function="internal">
        <lane id=":B_26_0" index="0" speed="3.65" length="3.23" shape="834.32,1122.28,8.69 833.52,1122.68,8.69 832.72,1122.28,8.69 831.92,1121.08,8.69" />
    </edge>
    <edge id=":B_15" function="internal">
        <lane id=":B_15_0" index="0" speed="6.51" length="9.03" shape="819.92,1126.68,8.69 822.37,1126.33,8.69 824.12,1125.28,8.69 825.17,1123.53,8.69 825.52,1121.08,8.69" />
    </edge>
    <edge id=":B_16" function="internal">
        <lane id=":B_16_0" index="0" speed="13.41" length="27.20" shape="819.92,1126.68,8.69 847.12,1126.68,8.69" />
        <lane id=":B_16_1" index="1" speed="13.41" length="27.20" shape="819.92,1129.88,8.69 847.12,1129.88,8.69" />
        <lane id=":B_16_2" index="2" speed="13.41" length="27.20" shape="819.92,1133.08,8.69 847.12,1133.08,8.69" />
    </edge>
    <edge id=":B_19" function="internal">
        <lane id=":B_19_0" index="0" speed="9.84" length="6.30" shape="819.92,1133.08,8.69 826.17,1133.79,8.69" />
    </edge>
    <edge id=":B_20" function="internal">
        <lane id=":B_20_0" index="0" speed="3.65" length="1.44" shape="819.92,1133.08,8.69 821.12,1133.88,8.69" />
    </edge>
    <edge id=":B_27" function="internal">
        <lane id=":B_27_0" index="0" speed="9.84" length="15.70" shape="826.17,1133.79,8.69 826.57,1133.83,8.69 831.32,1136.08,8.69 834.17,1139.83,8.69 835.12,1145.08,8.69" />
    </edge>
    <edge id=":B_28" function="internal">
        <lane id=":B_28_0" index="0" speed="3.65" length="3.23" shape="821.12,1133.88,8.69 821.52,1134.68,8.69 821.12,1135.48,8.69 819.92,1136.28,8.69" />
    </edge>
    <edge id=":BA_0" function="internal">
        <lane id=":BA_0_0" index="0" speed="3.65" length="4.67" shape="835.12,1305.56,8.69 834.32,1306.76,8.69 833.52,1307.16,8.69 832.72,1306.76,8.69 831.92,1305.56,8.69" />
    </edge>
    <edge id=":BB_0" function="internal">
        <lane id=":BB_0_0" index="0" speed="3.65" length="4.67" shape="1004.40,1133.08,8.69 1005.60,1133.88,8.69 1006.00,1134.68,8.69 1005.60,1135.48,8.69 1004.40,1136.28,8.69" />
    </edge>
    <edge id=":BC_0" function="internal">
        <lane id=":BC_0_0" index="0" speed="3.65" length="4.67" shape="831.92,963.80,8.69 832.72,962.60,8.69 833.52,962.20,8.69 834.32,962.60,8.69 835.12,963.80,8.69" />
    </edge>
    <edge id=":B_intern_0" function="internal">
        <lane id=":B_intern_0_0" index="0" speed="13.41" length="8.55" shape="716.63,1139.48,2.77 714.17,1139.98,2.65 712.63,1141.08,2.56 711.10,1142.18,2.46 708.63,1142.68,2.34" />
        <lane id=":B_intern_0_1" index="1" speed="13.41" length="8.55" shape="716.63,1136.28,2.77 714.17,1136.78,2.65 712.63,1137.88,2.56 711.10,1138.98,2.46 708.63,1139.48,2.34" />
        <lane id=":B_intern_0_2" index="2" speed="13.41" length="8.55" shape="716.63,1136.28,2.77 708.63,1136.28,2.34" />
    </edge>
    <edge id=":C_0" function="internal">
        <lane id=":C_0_0" index="0" speed="6.51" length="9.03" shape="661.03,574.54,3.41 660.68,572.09,3.43 659.63,570.34,3.44 657.88,569.29,3.45 655.43,568.94,3.46" />
    </edge>
    <edge id=":C_1" function="internal">
        <lane id=":C_1_0" index="0" speed="11.18" length="14.40" shape="661.03,574.54,3.41 661.03,560.14,3.46" />
    </edge>
    <edge id=":C_2" function="internal">
        <lane id=":C_2_0" index="0" speed="8.00" length="4.07" shape="661.03,574.54,3.41 661.58,570.69,3.43 661.68,570.54,3.43" />
    </edge>
    <edge id=":C_3" function="internal">
        <lane id=":C_3_0" index="0" speed="3.65" length="1.44" shape="661.03,574.54,3.41 661.83,573.34,3.41" />
    </edge>
    <edge id=":C_16" function="internal">
        <lane id=":C_16_0" index="0" speed="8.00" length="10.13" shape="661.68,570.54,3.43 663.23,567.94,3.44 665.98,566.29,3.45 669.83,565.74,3.46" />
    </edge>
    <edge id=":C_17" function="internal">
        <lane id=":C_17_0" index="0" speed="3.65" length="3.23" shape="661.83,573.34,3.41 662.63,572.94,3.41 663.43,573.34,3.41 664.23,574.54,3.41" />
    </edge>
    <edge id=":C_4" function="internal">
        <lane id=":C_4_0" index="0" speed="6.51" length="9.03" shape="669.83,568.94,3.46 667.38,569.29,3.45 665.63,570.34,3.44 664.58,572.09,3.43 664.23,574.54,3.41" />
    </edge>
    <edge id=":C_5" function="internal">
        <lane id=":C_5_0" index="0" speed="11.18" length="14.40" shape="669.83,568.94,3.46 655.43,568.94,3.46" />
    </edge>
    <edge id=":C_6" function="internal">
        <lane id=":C_6_0" index="0" speed="8.00" length="4.07" shape="669.83,568.94,3.46 665.98,568.39,3.46 665.83,568.30,3.46" />
    </edge>
    <edge id=":C_7" function="internal">
        <lane id=":C_7_0" index="0" speed="3.65" length="1.44" shape="669.83,568.94,3.46 668.63,568.14,3.46" />
    </edge>
    <edge id=":C_18" function="internal">
        <lane id=":C_18_0" index="0" speed="8.00" length="10.13" shape="665.83,568.30,3.46 663.23,566.74,3.46 661.58,563.99,3.46 661.03,560.14,3.46" />
    </edge>
    <edge id=":C_19" function="internal">
        <lane id=":C_19_0" index="0" speed="3.65" length="3.23" shape="668.63,568.14,3.46 668.23,567.34,3.46 668.63,566.54,3.46 669.83,565.74,3.46" />
    </edge>
    <edge id=":C_8" function="internal">
        <lane id=":C_8_0" index="0" speed="6.51" length="9.03" shape="664.23,560.14,3.46 664.58,562.59,3.46 665.63,564.34,3.46 667.38,565.39,3.46 669.83,565.74,3.46" />
    </edge>
    <edge id=":C_9" function="internal">
        <lane id=":C_9_0" index="0" speed="11.18" length="14.40" shape="664.23,560.14,3.46 664.23,574.54,3.41" />
    </edge>
    <edge id=":C_10" function="internal">
        <lane id=":C_10_0" index="0" speed="8.00" length="4.07" shape="664.23,560.14,3.46 663.68,563.99,3.46 663.59,564.14,3.46" />
    </edge>
    <edge id=":C_11" function="internal">
        <lane id=":C_11_0" index="0" speed="3.65" length="1.44" shape="664.23,560.14,3.46 663.43,561.34,3.46" />
    </edge>
    <edge id=":C_20" function="internal">
        <lane id=":C_20_0" index="0" speed="8.00" length="10.13" shape="663.59,564.14,3.46 662.03,566.74,3.46 659.28,568.39,3.46 655.43,568.94,3.46" />
    </edge>
    <edge id=":C_21" function="internal">
        <lane id=":C_21_0" index="0" speed="3.65" length="3.23" shape="663.43,561.34,3.46 662.63,561.74,3.46 661.83,561.34,3.46 661.03,560.14,3.46" />
    </edge>
    <edge id=":C_12" function="internal">
        <lane id=":C_12_0" index="0" speed="6.51" length="9.03" shape="655.43,565.74,3.46 657.88,565.39,3.46 659.63,564.34,3.46 660.68,562.59,3.46 661.03,560.14,3.46" />
    </edge>
    <edge id=":C_13" function="internal">
        <lane id=":C_13_0" index="0" speed="11.18" length="14.40" shape="655.43,565.74,3.46 669.83,565.74,3.46" />
    </edge>
    <edge id=":C_14" function="internal">
        <lane id=":C_14_0" index="0" speed="8.00" length="4.07" shape="655.43,565.74,3.46 659.28,566.29,3.45 659.44,566.38,3.45" />
    </edge>
    <edge id=":C_15" function="internal">
        <lane id=":C_15_0" index="0" speed="3.65" length="1.44" shape="655.43,565.74,3.46 656.63,566.54,3.46" />
    </edge>
    <edge id=":C_22" function="internal">
        <lane id=":C_22_0" index="0" speed="8.00" length="10.13" shape="659.44,566.38,3.45 662.03,567.94,3.44 663.68,570.69,3.43 664.23,574.54,3.41" />
    </edge>
    <edge id=":C_23" function="internal">
        <lane id=":C_23_0" index="0" speed="3.65" length="3.23" shape="656.63,566.54,3.46 657.03,567.34,3.46 656.63,568.14,3.46 655.43,568.94,3.46" />
    </edge>
    <edge id=":CA_0" function="internal">
        <lane id=":CA_0_0" index="0" speed="3.65" length="4.67" shape="1229.97,565.74,3.46 1231.17,566.54,3.46 1231.57,567.34,3.46 1231.17,568.14,3.46 1229.97,568.94,3.46" />
    </edge>
    <edge id=":CB_0" function="internal">
        <lane id=":CB_0_0" index="0" speed="3.65" length="4.67" shape="661.03,-0.00,3.46 661.83,-1.20,3.46 662.63,-1.60,3.46 663.43,-1.20,3.46 664.23,-0.00,3.46" />
    </edge>
    <edge id=":CC_0" function="internal">
        <lane id=":CC_0_0" index="0" speed="3.65" length="4.67" shape="95.29,568.94,3.46 94.09,568.14,3.46 93.69,567.34,3.46 94.09,566.54,3.46 95.29,565.74,3.46" />
    </edge>
    <edge id=":D_0" function="internal">
        <lane id=":D_0_0" index="0" speed="6.51" length="9.03" shape="323.32,1145.08,23.31 322.97,1142.63,23.31 321.92,1140.88,23.31 320.17,1139.83,23.31 317.72,1139.48,23.31" />
    </edge>
    <edge id=":D_1" function="internal">
        <lane id=":D_1_0" index="0" speed="17.88" length="24.27" shape="323.32,1145.08,23.31 323.82,1137.63,23.31 324.92,1132.29,23.31 326.02,1127.35,23.31 326.52,1121.08,23.31" />
        <lane id=":D_1_1" index="1" speed="17.88" length="24.27" shape="326.52,1145.08,23.31 327.02,1137.63,23.31 328.12,1132.29,23.31 329.22,1127.35,23.31 329.72,1121.08,23.31" />
    </edge>
    <edge id=":D_3" function="internal">
        <lane id=":D_3_0" index="0" speed="9.84" length="5.46" shape="329.72,1145.08,23.31 330.67,1139.83,23.31 330.75,1139.73,23.31" />
    </edge>
    <edge id=":D_4" function="internal">
        <lane id=":D_4_0" index="0" speed="3.65" length="1.44" shape="329.72,1145.08,23.31 330.52,1143.88,23.31" />
    </edge>
    <edge id=":D_21" function="internal">
        <lane id=":D_21_0" index="0" speed="9.84" length="16.53" shape="330.75,1139.73,23.31 333.52,1136.08,23.31 338.27,1133.83,23.31 344.92,1133.08,23.31" />
    </edge>
    <edge id=":D_22" function="internal">
        <lane id=":D_22_0" index="0" speed="3.65" length="3.23" shape="330.52,1143.88,23.31 331.32,1143.48,23.31 332.12,1143.88,23.31 332.92,1145.08,23.31" />
    </edge>
    <edge id=":D_5" function="internal">
        <lane id=":D_5_0" index="0" speed="7.33" length="11.73" shape="344.92,1139.48,23.31 341.07,1139.83,23.31 338.32,1140.88,23.31 336.67,1142.63,23.31 336.12,1145.08,23.31" />
    </edge>
    <edge id=":D_6" function="internal">
        <lane id=":D_6_0" index="0" speed="17.88" length="27.20" shape="344.92,1139.48,23.31 317.72,1139.48,23.31" />
        <lane id=":D_6_1" index="1" speed="17.88" length="27.20" shape="344.92,1136.28,23.31 317.72,1136.28,23.31" />
    </edge>
    <edge id=":D_8" function="internal">
        <lane id=":D_8_0" index="0" speed="10.36" length="5.01" shape="344.92,1136.28,23.31 339.95,1135.57,23.31" />
    </edge>
    <edge id=":D_9" function="internal">
        <lane id=":D_9_0" index="0" speed="3.65" length="1.44" shape="344.92,1136.28,23.31 343.72,1135.48,23.31" />
    </edge>
    <edge id=":D_23" function="internal">
        <lane id=":D_23_0" index="0" speed="10.36" length="19.50" shape="339.95,1135.57,23.31 338.27,1135.33,23.31 333.52,1132.48,23.31 330.67,1127.73,23.31 329.72,1121.08,23.31" />
    </edge>
    <edge id=":D_24" function="internal">
        <lane id=":D_24_0" index="0" speed="3.65" length="3.23" shape="343.72,1135.48,23.31 343.32,1134.68,23.31 343.72,1133.88,23.31 344.92,1133.08,23.31" />
    </edge>
    <edge id=":D_10" function="internal">
        <lane id=":D_10_0" index="0" speed="6.51" length="9.03" shape="339.32,1121.08,23.31 339.67,1123.53,23.31 340.72,1125.28,23.31 342.47,1126.33,23.31 344.92,1126.68,23.31" />
    </edge>
    <edge id=":D_11" function="internal">
        <lane id=":D_11_0" index="0" speed="17.88" length="24.27" shape="339.32,1121.08,23.31 338.82,1128.53,23.31 337.72,1133.87,23.31 336.62,1138.81,23.31 336.12,1145.08,23.31" />
        <lane id=":D_11_1" index="1" speed="17.88" length="24.27" shape="336.12,1121.08,23.31 335.62,1128.53,23.31 334.52,1133.87,23.31 333.42,1138.81,23.31 332.92,1145.08,23.31" />
    </edge>
    <edge id=":D_13" function="internal">
        <lane id=":D_13_0" index="0" speed="10.36" length="7.35" shape="332.92,1121.08,23.31 331.97,1127.73,23.31 331.64,1128.27,23.31" />
    </edge>
    <edge id=":D_14" function="internal">
        <lane id=":D_14_0" index="0" speed="3.65" length="1.44" shape="332.92,1121.08,23.31 332.12,1122.28,23.31" />
    </edge>
    <edge id=":D_25" function="internal">
        <lane id=":D_25_0" index="0" speed="10.36" length="17.17" shape="331.64,1128.27,23.31 329.12,1132.48,23.31 324.37,1135.33,23.31 317.72,1136.28,23.31" />
    </edge>
    <edge id=":D_26" function="internal">
        <lane id=":D_26_0" index="0" speed="3.65" length="3.23" shape="332.12,1122.28,23.31 331.32,1122.68,23.31 330.52,1122.28,23.31 329.72,1121.08,23.31" />
    </edge>
    <edge id=":D_15" function="internal">
        <lane id=":D_15_0" index="0" speed="7.33" length="11.73" shape="317.72,1126.68,23.31 321.57,1126.33,23.31 324.32,1125.28,23.31 325.97,1123.53,23.31 326.52,1121.08,23.31" />
    </edge>
    <edge id=":D_16" function="internal">
        <lane id=":D_16_0" index="0" speed="17.88" length="27.20" shape="317.72,1126.68,23.31 344.92,1126.68,23.31" />
        <lane id=":D_16_1" index="1" speed="17.88" length="27.20" shape="317.72,1129.88,23.31 344.92,1129.88,23.31" />
        <lane id=":D_16_2" index="2" speed="17.88" length="27.20" shape="317.72,1133.08,23.31 344.92,1133.08,23.31" />
    </edge>
    <edge id=":D_19" function="internal">
        <lane id=":D_19_0" index="0" speed="9.84" length="6.30" shape="317.72,1133.08,23.31 323.97,1133.79,23.31" />
    </edge>
    <edge id=":D_20" function="internal">
        <lane id=":D_20_0" index="0" speed="3.65" length="1.44" shape="317.72,1133.08,23.31 318.92,1133.88,23.31" />
    </edge>
    <edge id=":D_27" function="internal">
        <lane id=":D_27_0" index="0" speed="9.84" length="15.70" shape="323.97,1133.79,23.31 324.37,1133.83,23.31 329.12,1136.08,23.31 331.97,1139.83,23.31 332.92,1145.08,23.31" />
    </edge>
    <edge id=":D_28" function="internal">
        <lane id=":D_28_0" index="0" speed="3.65" length="3.23" shape="318.92,1133.88,23.31 319.32,1134.68,23.31 318.92,1135.48,23.31 317.72,1136.28,23.31" />
    </edge>
    <edge id=":DA_0" function="internal">
        <lane id=":DA_0_0" index="0" speed="3.65" length="4.67" shape="329.72,803.36,23.31 330.52,802.16,23.31 331.32,801.76,23.31 332.12,802.16,23.31 332.92,803.36,23.31" />
    </edge>
    <edge id=":DB_0" function="internal">
        <lane id=":DB_0_0" index="0" speed="3.65" length="4.67" shape="0.00,1136.28,23.31 -1.20,1135.48,23.31 -1.60,1134.68,23.31 -1.20,1133.88,23.31 0.00,1133.08,23.31" />
    </edge>
    <edge id=":DC_0" function="internal">
        <lane id=":DC_0_0" index="0" speed="3.65" length="4.67" shape="332.92,1466.00,23.31 332.12,1467.20,23.31 331.32,1467.60,23.31 330.52,1467.20,23.31 329.72,1466.00,23.31" />
    </edge>
    <edge id=":TL_0" function="internal">
        <lane id=":TL_0_0" index="0" speed="6.51" length="9.03" shape="669.83,1142.68 667.38,1143.03 665.63,1144.08 664.58,1145.83 664.23,1148.28" />
    </edge>
    <edge id=":TL_1" function="internal">
        <lane id=":TL_1_0" index="0" speed="15.65" length="14.86" shape="669.83,1142.68 665.51,1142.18 662.63,1141.08 659.76,1139.98 655.43,1139.48" />
        <lane id=":TL_1_1" index="1" speed="15.65" length="14.86" shape="669.83,1139.48 665.51,1138.98 662.63,1137.88 659.76,1136.78 655.43,1136.28" />
    </edge>
    <edge id=":TL_3" function="internal">
        <lane id=":TL_3_0" index="0" speed="9.32" length="7.76" shape="669.83,1136.28 665.98,1135.33,0.02 663.35,1132.60,0.03" />
    </edge>
    <edge id=":TL_10" function="internal">
        <lane id=":TL_10_0" index="0" speed="9.32" length="11.87" shape="663.35,1132.60,0.03 663.23,1132.48,0.03 661.58,1127.73,0.05 661.03,1121.08,0.08" />
    </edge>
    <edge id=":TL_4" function="internal">
        <lane id=":TL_4_0" index="0" speed="6.51" length="9.03" shape="664.23,1121.08,0.08 664.58,1123.53,0.06 665.63,1125.28,0.04 667.38,1126.33,0.02 669.83,1126.68" />
    </edge>
    <edge id=":TL_5" function="internal">
        <lane id=":TL_5_0" index="0" speed="11.18" length="27.20" shape="664.23,1121.08,0.08 664.23,1148.28" />
    </edge>
    <edge id=":TL_6" function="internal">
        <lane id=":TL_6_0" index="0" speed="6.51" length="9.03" shape="655.43,1126.68 657.88,1126.33,0.02 659.63,1125.28,0.04 660.68,1123.53,0.06 661.03,1121.08,0.08" />
    </edge>
    <edge id=":TL_7" function="internal">
        <lane id=":TL_7_0" index="0" speed="15.65" length="14.40" shape="655.43,1126.68 669.83,1126.68" />
        <lane id=":TL_7_1" index="1" speed="15.65" length="14.40" shape="655.43,1129.88 669.83,1129.88" />
    </edge>
    <edge id=":TL_9" function="internal">
        <lane id=":TL_9_0" index="0" speed="9.32" length="3.97" shape="655.43,1133.08 659.28,1134.03" />
    </edge>
    <edge id=":TL_11" function="internal">
        <lane id=":TL_11_0" index="0" speed="9.32" length="15.66" shape="659.28,1134.03 662.03,1136.88 663.68,1141.63 664.23,1148.28" />
    </edge>

    <edge id="A2AA" from="A" to="AA" priority="-1">
        <lane id="A2AA_0" index="0" speed="11.18" length="302.30" shape="658.63,1442.58,5.13 356.33,1442.58,5.13" />
    </edge>
    <edge id="A2AB" from="A" to="AB" priority="-1">
        <lane id="A2AB_0" index="0" speed="11.18" length="299.10" shape="664.23,1448.18,5.13 664.23,1747.28,5.13" />
    </edge>
    <edge id="A2AC" from="A" to="AC" priority="-1">
        <lane id="A2AC_0" index="0" speed="11.18" length="299.10" shape="669.83,1439.38,5.13 968.93,1439.38,5.13" />
    </edge>
    <edge id="B2BA" from="B" to="BA" priority="-1">
        <lane id="B2BA_0" index="0" speed="13.41" length="160.48" shape="841.52,1145.08,8.69 841.52,1305.56,8.69" />
        <lane id="B2BA_1" index="1" speed="13.41" length="160.48" shape="838.32,1145.08,8.69 838.32,1305.56,8.69" />
        <lane id="B2BA_2" index="2" speed="13.41" length="160.48" shape="835.12,1145.08,8.69 835.12,1305.56,8.69" />
    </edge>
    <edge id="B2BB" from="B" to="BB" priority="-1">
        <lane id="B2BB_0" index="0" speed="13.41" length="157.28" shape="847.12,1126.68,8.69 1004.40,1126.68,8.69" />
        <lane id="B2BB_1" index="1" speed="13.41" length="157.28" shape="847.12,1129.88,8.69 1004.40,1129.88,8.69" />
        <lane id="B2BB_2" index="2" speed="13.41" length="157.28" shape="847.12,1133.08,8.69 1004.40,1133.08,8.69" />
    </edge>
    <edge id="B2BC" from="B" to="BC" priority="-1">
        <lane id="B2BC_0" index="0" speed="13.41" length="157.28" shape="825.52,1121.08,8.69 825.52,963.80,8.69" />
        <lane id="B2BC_1" index="1" speed="13.41" length="157.28" shape="828.72,1121.08,8.69 828.72,963.80,8.69" />
        <lane id="B2BC_2" index="2" speed="13.41" length="157.28" shape="831.92,1121.08,8.69 831.92,963.80,8.69" />
    </edge>
    <edge id="B2TL" from="B" to="B_intern" priority="-1">
        <lane id="B2TL_0" index="0" speed="13.41" length="103.45" shape="819.92,1139.48,8.69 716.63,1139.48,2.77" />
        <lane id="B2TL_1" index="1" speed="13.41" length="103.45" shape="819.92,1136.28,8.69 716.63,1136.28,2.77" />
    </edge>
    <edge id="B2TL_intern" from="B_intern" to="TL" priority="-1">
        <lane id="B2TL_intern_0" index="0" speed="13.41" length="38.87" shape="708.63,1142.68,2.34 669.83,1142.68" />
        <lane id="B2TL_intern_1" index="1" speed="13.41" length="38.87" shape="708.63,1139.48,2.34 669.83,1139.48" />
        <lane id="B2TL_intern_2" index="2" speed="13.41" length="38.87" shape="708.63,1136.28,2.34 669.83,1136.28" />
    </edge>
    <edge id="BA2B" from="BA" to="B" priority="-1">
        <lane id="BA2B_0" index="0" speed="13.41" length="160.48" shape="828.72,1305.56,8.69 828.72,1145.08,8.69" />
        <lane id="BA2B_1" index="1" speed="13.41" length="160.48" shape="831.92,1305.56,8.69 831.92,1145.08,8.69" />
    </edge>
    <edge id="BB2B" from="BB" to="B" priority="-1">
        <lane id="BB2B_0" index="0" speed="13.41" length="157.28" shape="1004.40,1139.48,8.69 847.12,1139.48,8.69" />
        <lane id="BB2B_1" index="1" speed="13.41" length="157.28" shape="1004.40,1136.28,8.69 847.12,1136.28,8.69" />
    </edge>
    <edge id="BC2B" from="BC" to="B" priority="-1">
        <lane id="BC2B_0" index="0" speed="13.41" length="157.28" shape="838.32,963.80,8.69 838.32,1121.08,8.69" />
        <lane id="BC2B_1" index="1" speed="13.41" length="157.28" shape="835.12,963.80,8.69 835.12,1121.08,8.69" />
    </edge>
    <edge id="C2CA" from="C" to="CA" priority="-1">
        <lane id="C2CA_0" index="0" speed="11.18" length="560.14" shape="669.83,565.74,3.46 1229.97,565.74,3.46" />
    </edge>
    <edge id="C2CB" from="C" to="CB" priority="-1">
        <lane id="C2CB_0" index="0" speed="11.18" length="560.14" shape="661.03,560.14,3.46 661.03,-0.00,3.46" />
    </edge>
    <edge id="C2CC" from="C" to="CC" priority="-1">
        <lane id="C2CC_0" index="0" speed="11.18" length="560.14" shape="655.43,568.94,3.46 95.29,568.94,3.46" />
    </edge>
    <edge id="C2TL" from="C" to="TL" priority="-1">
        <lane id="C2TL_0" index="0" speed="11.18" length="546.55" shape="664.23,574.54,3.41 664.23,1121.08,0.08" />
    </edge>
    <edge id="CA2C" from="CA" to="C" priority="-1">
        <lane id="CA2C_0" index="0" speed="11.18" length="560.14" shape="1229.97,568.94,3.46 669.83,568.94,3.46" />
    </edge>
    <edge id="CB2C" from="CB" to="C" priority="-1">
        <lane id="CB2C_0" index="0" speed="11.18" length="560.14" shape="664.23,-0.00,3.46 664.23,560.14,3.46" />
    </edge>
    <edge id="CC2C" from="CC" to="C" priority="-1">
        <lane id="CC2C_0" index="0" speed="11.18" length="560.14" shape="95.29,565.74,3.46 655.43,565.74,3.46" />
    </edge>
    <edge id="D2DA" from="D" to="DA" priority="-1">
        <lane id="D2DA_0" index="0" speed="17.88" length="317.72" shape="326.52,1121.08,23.31 326.52,803.36,23.31" />
        <lane id="D2DA_1" index="1" speed="17.88" length="317.72" shape="329.72,1121.08,23.31 329.72,803.36,23.31" />
    </edge>
    <edge id="D2DB" from="D" to="DB" priority="-1">
        <lane id="D2DB_0" index="0" speed="17.88" length="317.72" shape="317.72,1139.48,23.31 0.00,1139.48,23.31" />
        <lane id="D2DB_1" index="1" speed="17.88" length="317.72" shape="317.72,1136.28,23.31 0.00,1136.28,23.31" />
    </edge>
    <edge id="D2DC" from="D" to="DC" priority="-1">
        <lane id="D2DC_0" index="0" speed="17.88" length="320.92" shape="336.12,1145.08,23.31 336.12,1466.00,23.31" />
        <lane id="D2DC_1" index="1" speed="17.88" length="320.92" shape="332.92,1145.08,23.31 332.92,1466.00,23.31" />
    </edge>
    <edge id="D2TL" from="D" to="TL" priority="-1">
        <lane id="D2TL_0" index="0" speed="17.88" length="311.39" shape="344.92,1126.68,23.31 655.43,1126.68" />
        <lane id="D2TL_1" index="1" speed="17.88" length="311.39" shape="344.92,1129.88,23.31 655.43,1129.88" />
        <lane id="D2TL_2" index="2" speed="17.88" length="311.39" shape="344.92,1133.08,23.31 655.43,1133.08" />
    </edge>
    <edge id="DA2D" from="DA" to="D" priority="-1">
        <lane id="DA2D_0" index="0" speed="17.88" length="317.72" shape="339.32,803.36,23.31 339.32,1121.08,23.31" />
        <lane id="DA2D_1" index="1" speed="17.88" length="317.72" shape="336.12,803.36,23.31 336.12,1121.08,23.31" />
        <lane id="DA2D_2" index="2" speed="17.88" length="317.72" shape="332.92,803.36,23.31 332.92,1121.08,23.31" />
    </edge>
    <edge id="DB2D" from="DB" to="D" priority="-1">
        <lane id="DB2D_0" index="0" speed="17.88" length="317.72" shape="0.00,1126.68,23.31 317.72,1126.68,23.31" />
        <lane id="DB2D_1" index="1" speed="17.88" length="317.72" shape="0.00,1129.88,23.31 317.72,1129.88,23.31" />
        <lane id="DB2D_2" index="2" speed="17.88" length="317.72" shape="0.00,1133.08,23.31 317.72,1133.08,23.31" />
    </edge>
    <edge id="DC2D" from="DC" to="D" priority="-1">
        <lane id="DC2D_0" index="0" speed="17.88" length="320.92" shape="323.32,1466.00,23.31 323.32,1145.08,23.31" />
        <lane id="DC2D_1" index="1" speed="17.88" length="320.92" shape="326.52,1466.00,23.31 326.52,1145.08,23.31" />
        <lane id="DC2D_2" index="2" speed="17.88" length="320.92" shape="329.72,1466.00,23.31 329.72,1145.08,23.31" />
    </edge>
    <edge id="TL2A" from="TL" to="A" priority="-1">
        <lane id="TL2A_0" index="0" speed="11.18" length="285.54" shape="664.23,1148.28 664.23,1433.78,5.01" />
    </edge>
    <edge id="TL2B" from="TL" to="B" priority="-1">
        <lane id="TL2B_0" index="0" speed="13.41" length="150.33" shape="669.83,1126.68 819.92,1126.68,8.69" />
        <lane id="TL2B_1" index="1" speed="13.41" length="150.33" shape="669.83,1129.88 819.92,1129.88,8.69" />
        <lane id="TL2B_2" index="2" speed="13.41" length="150.33" shape="669.83,1133.08 819.92,1133.08,8.69" />
    </edge>
    <edge id="TL2C" from="TL" to="C" priority="-1">
        <lane id="TL2C_0" index="0" speed="11.18" length="546.55" shape="661.03,1121.08,0.08 661.03,574.54,3.41" />
    </edge>
    <edge id="TL2D" from="TL" to="D" priority="-1">
        <lane id="TL2D_0" index="0" speed="17.88" length="311.39" shape="655.43,1139.48 344.92,1139.48,23.31" />
        <lane id="TL2D_1" index="1" speed="17.88" length="311.39" shape="655.43,1136.28 344.92,1136.28,23.31" />
    </edge>

    <tlLogic id="A" type="static" programID="0" offset="0">
        <phase duration="82" state="GGG" />
        <phase duration="3" state="yyy" />
        <phase duration="5" state="rrr" />
    </tlLogic>
    <tlLogic id="B" type="static" programID="0" offset="0">
        <phase duration="42" state="rrrrrGGGggrrrrrGGGGgg" />
        <phase duration="3" state="rrrrryyyyyrrrrryyyyyy" />
        <phase duration="42" state="GGGggrrrrrGGGggrrrrrr" />
        <phase duration="3" state="yyyyyrrrrryyyyyrrrrrr" />
    </tlLogic>
    <tlLogic id="BA" type="static" programID="0" offset="0">
        <phase duration="82" state="G" />
        <phase duration="3" state="y" />
        <phase duration="5" state="r" />
    </tlLogic>
    <tlLogic id="BB" type="static" programID="0" offset="0">
        <phase duration="82" state="G" />
        <phase duration="3" state="y" />
        <phase duration="5" state="r" />
    </tlLogic>
    <tlLogic id="BC" type="static" programID="0" offset="0">
        <phase duration="82" state="G" />
        <phase duration="3" state="y" />
        <phase duration="5" state="r" />
    </tlLogic>
    <tlLogic id="C" type="static" programID="0" offset="0">
        <phase duration="42" state="GGggrrrrGGggrrrr" />
        <phase duration="3" state="yyyyrrrryyyyrrrr" />
        <phase duration="42" state="rrrrGGggrrrrGGgg" />
        <phase duration="3" state="rrrryyyyrrrryyyy" />
    </tlLogic>
    <tlLogic id="CA" type="static" programID="0" offset="0">
        <phase duration="82" state="G" />
        <phase duration="3" state="y" />
        <phase duration="5" state="r" />
    </tlLogic>
    <tlLogic id="CB" type="static" programID="0" offset="0">
        <phase duration="82" state="G" />
        <phase duration="3" state="y" />
        <phase duration="5" state="r" />
    </tlLogic>
    <tlLogic id="CC" type="static" programID="0" offset="0">
        <phase duration="82" state="G" />
        <phase duration="3" state="y" />
        <phase duration="5" state="r" />
    </tlLogic>
    <tlLogic id="D" type="static" programID="0" offset="0">
        <phase duration="36" state="GGGrrrrrrrGGGrrrrrrrr" />
        <phase duration="4" state="yyyrrrrrrryyyrrrrrrrr" />
        <phase duration="6" state="rrrGGrrrrrrrrGGrrrrrr" />
        <phase duration="4" state="rrryyrrrrrrrryyrrrrrr" />
        <phase duration="36" state="rrrrrGGGggrrrrrGGGGgg" />
        <phase duration="4" state="rrrrryyyyyrrrrryyyyyy" />
    </tlLogic>
    <tlLogic id="DA" type="static" programID="0" offset="0">
        <phase duration="81" state="G" />
        <phase duration="4" state="y" />
        <phase duration="5" state="r" />
    </tlLogic>
    <tlLogic id="DB" type="static" programID="0" offset="0">
        <phase duration="81" state="G" />
        <phase duration="4" state="y" />
        <phase duration="5" state="r" />
    </tlLogic>
    <tlLogic id="DC" type="static" programID="0" offset="0">
        <phase duration="81" state="G" />
        <phase duration="4" state="y" />
        <phase duration="5" state="r" />
    </tlLogic>
    <tlLogic id="TL" type="static" programID="0" offset="0">
        <phase duration="15" state="GGGrsrGGGr" />
        <phase duration="4" state="yyyrsryyyr" />
        <phase duration="15" state="rrrGsrrrrG" />
        <phase duration="4" state="rrrysrrrry" />
        <phase duration="35" state="srrrGGGrrr" />
        <phase duration="4" state="srrryyyrrr" />
    </tlLogic>

    <junction id="A" type="traffic_light" x="662.63" y="1440.98" z="5.13" incLanes="TL2A_0" intLanes=":A_0_0 :A_1_0 :A_2_0" shape="662.63,1448.18,5.13 665.83,1448.18,5.13 665.95,1445.98,5.13 666.28,1444.18,5.13 666.83,1442.78,5.13 667.61,1441.78,5.13 668.61,1441.18,5.13 669.83,1440.98,5.13 669.83,1437.78,5.13 667.61,1437.34,5.13 666.83,1436.78,5.13 666.28,1436.00,5.13 665.95,1435.00,5.13 665.83,1433.78,5.13 662.63,1433.78,5.13 662.52,1435.98,5.13 662.19,1437.78,5.13 661.63,1439.18,5.13 660.86,1440.18,5.13 659.86,1440.78,5.13 658.63,1440.98,5.13 658.63,1444.18,5.13 660.86,1444.62,5.13 661.63,1445.18,5.13 662.19,1445.96,5.13 662.52,1446.96,5.13">
        <request index="0" response="000" foes="000" cont="0" />
        <request index="1" response="000" foes="000" cont="0" />
        <request index="2" response="000" foes="000" cont="0" />
    </junction>
    <junction id="AA" type="dead_end" x="356.33" y="1440.98" z="5.13" incLanes="A2AA_0" intLanes="" shape="356.33,1444.18,5.13 356.33,1440.98,5.13" />
    <junction id="AB" type="dead_end" x="662.63" y="1747.28" z="5.13" incLanes="A2AB_0" intLanes="" shape="665.83,1747.28,5.13 662.63,1747.28,5.13" />
    <junction id="AC" type="dead_end" x="968.93" y="1440.98" z="5.13" incLanes="A2AC_0" intLanes="" shape="968.93,1437.78,5.13 968.93,1440.98,5.13" />
    <junction id="B" type="traffic_light" x="833.52" y="1134.68" z="8.69" incLanes="BA2B_0 BA2B_1 BB2B_0 BB2B_1 BC2B_0 BC2B_1 TL2B_0 TL2B_1 TL2B_2" intLanes=":B_0_0 :B_1_0 :B_1_1 :B_21_0 :B_22_0 :B_5_0 :B_6_0 :B_6_1 :B_23_0 :B_24_0 :B_10_0 :B_11_0 :B_11_1 :B_25_0 :B_26_0 :B_15_0 :B_16_0 :B_16_1 :B_16_2 :B_27_0 :B_28_0" shape="827.12,1145.08,8.69 843.12,1145.08,8.69 843.56,1142.86,8.69 844.12,1142.08,8.69 844.89,1141.52,8.69 845.89,1141.19,8.69 847.12,1141.08,8.69 847.12,1125.08,8.69 844.92,1124.97,8.69 843.12,1124.63,8.69 841.72,1124.08,8.69 840.72,1123.30,8.69 840.12,1122.30,8.69 839.92,1121.08,8.69 823.92,1121.08,8.69 823.47,1123.30,8.69 822.92,1124.08,8.69 822.14,1124.63,8.69 821.14,1124.97,8.69 819.92,1125.08,8.69 819.92,1141.08,8.69 822.12,1141.19,8.69 823.92,1141.52,8.69 825.32,1142.08,8.69 826.32,1142.86,8.69 826.92,1143.86,8.69">
        <request index="0" response="000000000000011000000" foes="000000000000011000000" cont="0" />
        <request index="1" response="011110000000111000000" foes="011110110000111000000" cont="0" />
        <request index="2" response="011110000000111000000" foes="011110110000111000000" cont="0" />
        <request index="3" response="011110001100111000000" foes="011110001101111000000" cont="1" />
        <request index="4" response="010000001100000000000" foes="010000001100000000000" cont="1" />
        <request index="5" response="000000000000000000000" foes="000000000000000000000" cont="0" />
        <request index="6" response="000000010000000001000" foes="110000011100000001111" cont="0" />
        <request index="7" response="000000010000000001000" foes="110000011100000001111" cont="0" />
        <request index="8" response="001110010000000001000" foes="001110111100000001110" cont="1" />
        <request index="9" response="001110000000000001000" foes="001110000000000001000" cont="1" />
        <request index="10" response="001110000000000000000" foes="001110000000000000000" cont="0" />
        <request index="11" response="011110000000111000000" foes="011110000000111011000" cont="0" />
        <request index="12" response="011110000000111000000" foes="011110000000111011000" cont="0" />
        <request index="13" response="011110000000111000110" foes="111110000000111000110" cont="1" />
        <request index="14" response="000000000000100000110" foes="000000000000100000110" cont="1" />
        <request index="15" response="000000000000000000000" foes="000000000000000000000" cont="0" />
        <request index="16" response="000000010000000001000" foes="000000011111100001110" cont="0" />
        <request index="17" response="000000010000000001000" foes="000000011111100001110" cont="0" />
        <request index="18" response="000000010000000001000" foes="000000011111100001110" cont="0" />
        <request index="19" response="000000010000011001000" foes="000000011100011011110" cont="1" />
        <request index="20" response="000000010000011000000" foes="000000010000011000000" cont="1" />
    </junction>
    <junction id="BA" type="traffic_light" x="833.52" y="1305.56" z="8.69" incLanes="B2BA_0 B2BA_1 B2BA_2" intLanes=":BA_0_0" shape="833.52,1305.56,8.69 843.12,1305.56,8.69 833.52,1305.56,8.69">
        <request index="0" response="0" foes="0" cont="0" />
    </junction>
    <junction id="BB" type="traffic_light" x="1004.40" y="1134.68" z="8.69" incLanes="B2BB_0 B2BB_1 B2BB_2" intLanes=":BB_0_0" shape="1004.40,1134.68,8.69 1004.40,1125.08,8.69 1004.40,1134.68,8.69">
        <request index="0" response="0" foes="0" cont="0" />
    </junction>
    <junction id="BC" type="traffic_light" x="833.52" y="963.80" z="8.69" incLanes="B2BC_0 B2BC_1 B2BC_2" intLanes=":BC_0_0" shape="833.52,963.80,8.69 823.92,963.80,8.69 833.52,963.80,8.69">
        <request index="0" response="0" foes="0" cont="0" />
    </junction>
    <junction id="B_intern" type="priority" x="712.63" y="1134.68" z="2.54" incLanes="B2TL_0 B2TL_1" intLanes=":B_intern_0_0 :B_intern_0_1 :B_intern_0_2" shape="716.63,1141.08,2.54 716.63,1134.68,2.54 708.63,1134.68,2.54 708.63,1144.28,2.54 711.67,1143.45,2.54 713.60,1141.91,2.54 714.84,1141.32,2.54">
        <request index="0" response="000" foes="000" cont="0" />
        <request index="1" response="000" foes="000" cont="0" />
        <request index="2" response="000" foes="000" cont="0" />
    </junction>
    <junction id="C" type="traffic_light" x="662.63" y="567.34" z="3.46" incLanes="TL2C_0 CA2C_0 CB2C_0 CC2C_0" intLanes=":C_0_0 :C_1_0 :C_16_0 :C_17_0 :C_4_0 :C_5_0 :C_18_0 :C_19_0 :C_8_0 :C_9_0 :C_20_0 :C_21_0 :C_12_0 :C_13_0 :C_22_0 :C_23_0" shape="659.43,574.54,3.46 665.83,574.54,3.46 666.28,572.32,3.46 666.83,571.54,3.46 667.61,570.98,3.46 668.61,570.65,3.46 669.83,570.54,3.46 669.83,564.14,3.46 667.61,563.70,3.46 666.83,563.14,3.46 666.28,562.36,3.46 665.95,561.36,3.46 665.83,560.14,3.46 659.43,560.14,3.46 658.99,562.36,3.46 658.43,563.14,3.46 657.66,563.70,3.46 656.66,564.03,3.46 655.43,564.14,3.46 655.43,570.54,3.46 657.66,570.98,3.46 658.43,571.54,3.46 658.99,572.32,3.46 659.32,573.32,3.46">
        <request index="0" response="0000000000000000" foes="1000010000100000" cont="0" />
        <request index="1" response="0100000001000000" foes="0111110001100000" cont="0" />
        <request index="2" response="0100001101000000" foes="0110011111100000" cont="1" />
        <request index="3" response="0100001000010000" foes="0100001000010000" cont="1" />
        <request index="4" response="0000001000000000" foes="0100001000001000" cont="0" />
        <request index="5" response="0000011000000111" foes="1100011000000111" cont="0" />
        <request index="6" response="0111011000000110" foes="0111111000000110" cont="1" />
        <request index="7" response="0010000100000100" foes="0010000100000100" cont="1" />
        <request index="8" response="0000000000000000" foes="0010000010000100" cont="0" />
        <request index="9" response="0100000001000000" foes="0110000001111100" cont="0" />
        <request index="10" response="0100000001000111" foes="1110000001100111" cont="1" />
        <request index="11" response="0001000001000010" foes="0001000001000010" cont="1" />
        <request index="12" response="0000000000000010" foes="0000100001000010" cont="0" />
        <request index="13" response="0000011100000110" foes="0000011111000110" cont="0" />
        <request index="14" response="0000011000110110" foes="0000011001111110" cont="1" />
        <request index="15" response="0000010000100001" foes="0000010000100001" cont="1" />
    </junction>
    <junction id="CA" type="traffic_light" x="1229.97" y="567.34" z="3.46" incLanes="C2CA_0" intLanes=":CA_0_0" shape="1229.97,567.34,3.46 1229.97,564.14,3.46 1229.97,567.34,3.46">
        <request index="0" response="0" foes="0" cont="0" />
    </junction>
    <junction id="CB" type="traffic_light" x="662.63" y="0.00" z="3.46" incLanes="C2CB_0" intLanes=":CB_0_0" shape="662.63,-0.00,3.46 659.43,-0.00,3.46 662.63,-0.00,3.46">
        <request index="0" response="0" foes="0" cont="0" />
    </junction>
    <junction id="CC" type="traffic_light" x="95.29" y="567.34" z="3.46" incLanes="C2CC_0" intLanes=":CC_0_0" shape="95.29,567.34,3.46 95.29,570.54,3.46 95.29,567.34,3.46">
        <request index="0" response="0" foes="0" cont="0" />
    </junction>
    <junction id="D" type="traffic_light" x="331.32" y="1134.68" z="23.31" incLanes="DC2D_0 DC2D_1 DC2D_2 TL2D_0 TL2D_1 DA2D_0 DA2D_1 DA2D_2 DB2D_0 DB2D_1 DB2D_2" intLanes=":D_0_0 :D_1_0 :D_1_1 :D_21_0 :D_22_0 :D_5_0 :D_6_0 :D_6_1 :D_23_0 :D_24_0 :D_10_0 :D_11_0 :D_11_1 :D_25_0 :D_26_0 :D_15_0 :D_16_0 :D_16_1 :D_16_2 :D_27_0 :D_28_0" shape="321.72,1145.08,23.31 337.72,1145.08,23.31 338.52,1142.86,23.31 339.52,1142.08,23.31 340.92,1141.52,23.31 342.72,1141.19,23.31 344.92,1141.08,23.31 344.92,1125.08,23.31 342.69,1124.63,23.31 341.92,1124.08,23.31 341.36,1123.30,23.31 341.03,1122.30,23.31 340.92,1121.08,23.31 324.92,1121.08,23.31 324.12,1123.30,23.31 323.12,1124.08,23.31 321.72,1124.63,23.31 319.92,1124.97,23.31 317.72,1125.08,23.31 317.72,1141.08,23.31 319.94,1141.52,23.31 320.72,1142.08,23.31 321.27,1142.86,23.31 321.61,1143.86,23.31">
        <request index="0" response="000000000000000000000" foes="000000000000011000000" cont="0" />
        <request index="1" response="010000000000100000000" foes="011111110000111000000" cont="0" />
        <request index="2" response="010000000000100000000" foes="011111110000111000000" cont="0" />
        <request index="3" response="010000001100100000000" foes="011110001101111000000" cont="1" />
        <request index="4" response="010000001100000000000" foes="010000001100000000000" cont="1" />
        <request index="5" response="000000001100000000000" foes="000000001100000000000" cont="0" />
        <request index="6" response="000000011100000001111" foes="110000011100000001111" cont="0" />
        <request index="7" response="000000011100000001111" foes="110000011100000001111" cont="0" />
        <request index="8" response="001110011100000001110" foes="001110111100000001110" cont="1" />
        <request index="9" response="001110000000000001000" foes="001110000000000001000" cont="1" />
        <request index="10" response="000000000000000000000" foes="001110000000000000000" cont="0" />
        <request index="11" response="010000000000100000000" foes="011110000000111111000" cont="0" />
        <request index="12" response="010000000000100000000" foes="011110000000111111000" cont="0" />
        <request index="13" response="010000000000100000110" foes="111110000000111000110" cont="1" />
        <request index="14" response="000000000000100000110" foes="000000000000100000110" cont="1" />
        <request index="15" response="000000000000000000110" foes="000000000000000000110" cont="0" />
        <request index="16" response="000000011110000001110" foes="000000011111100001110" cont="0" />
        <request index="17" response="000000011110000001110" foes="000000011111100001110" cont="0" />
        <request index="18" response="000000011110000001110" foes="000000011111100001110" cont="0" />
        <request index="19" response="000000011100011001110" foes="000000011100011011110" cont="1" />
        <request index="20" response="000000010000011000000" foes="000000010000011000000" cont="1" />
    </junction>
    <junction id="DA" type="traffic_light" x="331.32" y="803.36" z="23.31" incLanes="D2DA_0 D2DA_1" intLanes=":DA_0_0" shape="331.32,803.36,23.31 324.92,803.36,23.31 331.32,803.36,23.31">
        <request index="0" response="0" foes="0" cont="0" />
    </junction>
    <junction id="DB" type="traffic_light" x="0.00" y="1134.68" z="23.31" incLanes="D2DB_0 D2DB_1" intLanes=":DB_0_0" shape="0.00,1134.68,23.31 0.00,1141.08,23.31 0.00,1134.68,23.31">
        <request index="0" response="0" foes="0" cont="0" />
    </junction>
    <junction id="DC" type="traffic_light" x="331.32" y="1466.00" z="23.31" incLanes="D2DC_0 D2DC_1" intLanes=":DC_0_0" shape="331.32,1466.00,23.31 337.72,1466.00,23.31 331.32,1466.00,23.31">
        <request index="0" response="0" foes="0" cont="0" />
    </junction>
    <junction id="TL" type="traffic_light_right_on_red" x="662.63" y="1134.68" incLanes="B2TL_intern_0 B2TL_intern_1 B2TL_intern_2 C2TL_0 D2TL_0 D2TL_1 D2TL_2" intLanes=":TL_0_0 :TL_1_0 :TL_1_1 :TL_10_0 :TL_4_0 :TL_5_0 :TL_6_0 :TL_7_0 :TL_7_1 :TL_11_0" shape="662.63,1148.28 665.83,1148.28 666.28,1146.06 666.83,1145.28 667.61,1144.72 668.61,1144.39 669.83,1144.28 669.83,1125.08 667.61,1124.63 666.83,1124.08 666.28,1123.30 665.95,1122.30 665.83,1121.08 659.43,1121.08 658.99,1123.30 658.43,1124.08 657.66,1124.63 656.66,1124.97 655.43,1125.08 655.43,1141.08 657.63,1141.28 659.43,1141.88 660.83,1142.88 661.83,1144.28 662.43,1146.08">
        <request index="0" response="0000100000" foes="1000100000" cont="0" />
        <request index="1" response="0000000000" foes="1000100000" cont="0" />
        <request index="2" response="0000000000" foes="1000100000" cont="0" />
        <request index="3" response="0111000000" foes="0111100000" cont="1" />
        <request index="4" response="0110000000" foes="0110000000" cont="0" />
        <request index="5" response="1110001111" foes="1110001111" cont="0" />
        <request index="6" response="0000000000" foes="0000001000" cont="0" />
        <request index="7" response="0000000000" foes="0000111000" cont="0" />
        <request index="8" response="0000000000" foes="0000111000" cont="0" />
        <request index="9" response="0000000111" foes="0000100111" cont="1" />
    </junction>

    <junction id=":B_21_0" type="internal" x="832.63" y="1141.13" z="8.69" incLanes=":B_3_0 BC2B_0 BC2B_1" intLanes=":B_6_0 :B_6_1 :B_8_0 :B_9_0 :B_10_0 :B_11_0 :B_11_1 :B_16_0 :B_16_1 :B_16_2 :B_19_0" />
    <junction id=":B_22_0" type="internal" x="832.72" y="1143.88" z="8.69" incLanes=":B_4_0 BB2B_0 BC2B_0 BC2B_1 TL2B_2" intLanes=":B_5_0 :B_11_0 :B_11_1 :B_19_0" />
    <junction id=":B_23_0" type="internal" x="842.15" y="1135.57" z="8.69" incLanes=":B_8_0 TL2B_0 TL2B_1 TL2B_2" intLanes=":B_1_0 :B_1_1 :B_3_0 :B_11_0 :B_11_1 :B_13_0 :B_14_0 :B_15_0 :B_16_0 :B_16_1 :B_16_2" />
    <junction id=":B_24_0" type="internal" x="845.92" y="1135.48" z="8.69" incLanes=":B_9_0 BA2B_1 BC2B_0 TL2B_0 TL2B_1 TL2B_2" intLanes=":B_3_0 :B_10_0 :B_16_0 :B_16_1 :B_16_2" />
    <junction id=":B_25_0" type="internal" x="834.41" y="1126.04" z="8.69" incLanes=":B_13_0 BA2B_0 BA2B_1" intLanes=":B_0_0 :B_1_0 :B_1_1 :B_6_0 :B_6_1 :B_8_0 :B_16_0 :B_16_1 :B_16_2 :B_19_0 :B_20_0" />
    <junction id=":B_26_0" type="internal" x="834.32" y="1122.28" z="8.69" incLanes=":B_14_0 BA2B_0 BA2B_1 BB2B_1 TL2B_0" intLanes=":B_1_0 :B_1_1 :B_8_0 :B_15_0" />
    <junction id=":B_27_0" type="internal" x="826.17" y="1133.79" z="8.69" incLanes=":B_19_0 BB2B_0 BB2B_1" intLanes=":B_1_0 :B_1_1 :B_3_0 :B_4_0 :B_5_0 :B_6_0 :B_6_1 :B_11_0 :B_11_1 :B_13_0" />
    <junction id=":B_28_0" type="internal" x="821.12" y="1133.88" z="8.69" incLanes=":B_20_0 BA2B_0 BB2B_0 BB2B_1 BC2B_1" intLanes=":B_0_0 :B_6_0 :B_6_1 :B_13_0" />
    <junction id=":C_16_0" type="internal" x="661.68" y="570.54" z="3.43" incLanes=":C_2_0 CB2C_0" intLanes=":C_5_0 :C_6_0 :C_7_0 :C_8_0 :C_9_0 :C_13_0 :C_14_0" />
    <junction id=":C_17_0" type="internal" x="661.83" y="573.34" z="3.41" incLanes=":C_3_0 CA2C_0 CB2C_0 CC2C_0" intLanes=":C_4_0 :C_9_0 :C_14_0" />
    <junction id=":C_18_0" type="internal" x="665.83" y="568.30" z="3.46" incLanes=":C_6_0 CC2C_0" intLanes=":C_1_0 :C_2_0 :C_9_0 :C_10_0 :C_11_0 :C_12_0 :C_13_0" />
    <junction id=":C_19_0" type="internal" x="668.63" y="568.14" z="3.46" incLanes=":C_7_0 CB2C_0 CC2C_0 TL2C_0" intLanes=":C_2_0 :C_8_0 :C_13_0" />
    <junction id=":C_20_0" type="internal" x="663.59" y="564.14" z="3.46" incLanes=":C_10_0 TL2C_0" intLanes=":C_0_0 :C_1_0 :C_5_0 :C_6_0 :C_13_0 :C_14_0 :C_15_0" />
    <junction id=":C_21_0" type="internal" x="663.43" y="561.34" z="3.46" incLanes=":C_11_0 CA2C_0 CC2C_0 TL2C_0" intLanes=":C_1_0 :C_6_0 :C_12_0" />
    <junction id=":C_22_0" type="internal" x="659.44" y="566.38" z="3.45" incLanes=":C_14_0 CA2C_0" intLanes=":C_1_0 :C_2_0 :C_3_0 :C_4_0 :C_5_0 :C_9_0 :C_10_0" />
    <junction id=":C_23_0" type="internal" x="656.63" y="566.54" z="3.46" incLanes=":C_15_0 CA2C_0 CB2C_0 TL2C_0" intLanes=":C_0_0 :C_5_0 :C_10_0" />
    <junction id=":D_21_0" type="internal" x="330.75" y="1139.73" z="23.31" incLanes=":D_3_0 DA2D_0 DA2D_1" intLanes=":D_6_0 :D_6_1 :D_8_0 :D_9_0 :D_10_0 :D_11_0 :D_11_1 :D_16_0 :D_16_1 :D_16_2 :D_19_0" />
    <junction id=":D_22_0" type="internal" x="330.52" y="1143.88" z="23.31" incLanes=":D_4_0 DA2D_0 DA2D_1 DB2D_2 TL2D_0" intLanes=":D_5_0 :D_11_0 :D_11_1 :D_19_0" />
    <junction id=":D_23_0" type="internal" x="339.95" y="1135.57" z="23.31" incLanes=":D_8_0 DB2D_0 DB2D_1 DB2D_2" intLanes=":D_1_0 :D_1_1 :D_3_0 :D_11_0 :D_11_1 :D_13_0 :D_14_0 :D_15_0 :D_16_0 :D_16_1 :D_16_2" />
    <junction id=":D_24_0" type="internal" x="343.72" y="1135.48" z="23.31" incLanes=":D_9_0 DA2D_0 DB2D_0 DB2D_1 DB2D_2 DC2D_2" intLanes=":D_3_0 :D_10_0 :D_16_0 :D_16_1 :D_16_2" />
    <junction id=":D_25_0" type="internal" x="331.64" y="1128.27" z="23.31" incLanes=":D_13_0 DC2D_0 DC2D_1" intLanes=":D_0_0 :D_1_0 :D_1_1 :D_6_0 :D_6_1 :D_8_0 :D_16_0 :D_16_1 :D_16_2 :D_19_0 :D_20_0" />
    <junction id=":D_26_0" type="internal" x="332.12" y="1122.28" z="23.31" incLanes=":D_14_0 DB2D_0 DC2D_0 DC2D_1 TL2D_1" intLanes=":D_1_0 :D_1_1 :D_8_0 :D_15_0" />
    <junction id=":D_27_0" type="internal" x="323.97" y="1133.79" z="23.31" incLanes=":D_19_0 TL2D_0 TL2D_1" intLanes=":D_1_0 :D_1_1 :D_3_0 :D_4_0 :D_5_0 :D_6_0 :D_6_1 :D_11_0 :D_11_1 :D_13_0" />
    <junction id=":D_28_0" type="internal" x="318.92" y="1133.88" z="23.31" incLanes=":D_20_0 DA2D_2 DC2D_0 TL2D_0 TL2D_1" intLanes=":D_0_0 :D_6_0 :D_6_1 :D_13_0" />
    <junction id=":TL_10_0" type="internal" x="663.35" y="1132.60" z="0.03" incLanes=":TL_3_0 D2TL_0 D2TL_1" intLanes=":TL_5_0 :TL_6_0 :TL_7_0 :TL_7_1" />
    <junction id=":TL_11_0" type="internal" x="659.28" y="1134.03" incLanes=":TL_9_0 B2TL_intern_0 B2TL_intern_1" intLanes=":TL_0_0 :TL_1_0 :TL_1_1 :TL_5_0" />

    <connection from="B2BA" to="BA2B" fromLane="2" toLane="1" via=":BA_0_0" tl="BA" linkIndex="0" dir="t" state="O" />
    <connection from="B2BB" to="BB2B" fromLane="2" toLane="1" via=":BB_0_0" tl="BB" linkIndex="0" dir="t" state="O" />
    <connection from="B2BC" to="BC2B" fromLane="2" toLane="1" via=":BC_0_0" tl="BC" linkIndex="0" dir="t" state="O" />
    <connection from="B2TL" to="B2TL_intern" fromLane="0" toLane="0" via=":B_intern_0_0" dir="s" state="M" />
    <connection from="B2TL" to="B2TL_intern" fromLane="1" toLane="1" via=":B_intern_0_1" dir="s" state="M" />
    <connection from="B2TL" to="B2TL_intern" fromLane="1" toLane="2" via=":B_intern_0_2" dir="s" state="M" />
    <connection from="B2TL_intern" to="TL2A" fromLane="0" toLane="0" via=":TL_0_0" tl="TL" linkIndex="0" dir="r" state="O" />
    <connection from="B2TL_intern" to="TL2D" fromLane="0" toLane="0" via=":TL_1_0" tl="TL" linkIndex="1" dir="s" state="O" />
    <connection from="B2TL_intern" to="TL2D" fromLane="1" toLane="1" via=":TL_1_1" tl="TL" linkIndex="2" dir="s" state="O" />
    <connection from="B2TL_intern" to="TL2C" fromLane="2" toLane="0" via=":TL_3_0" tl="TL" linkIndex="3" dir="l" state="o" />
    <connection from="BA2B" to="B2TL" fromLane="0" toLane="0" via=":B_0_0" tl="B" linkIndex="0" dir="r" state="o" />
    <connection from="BA2B" to="B2BC" fromLane="0" toLane="1" via=":B_1_0" tl="B" linkIndex="1" dir="s" state="o" />
    <connection from="BA2B" to="B2BC" fromLane="1" toLane="2" via=":B_1_1" tl="B" linkIndex="2" dir="s" state="o" />
    <connection from="BA2B" to="B2BB" fromLane="1" toLane="2" via=":B_3_0" tl="B" linkIndex="3" dir="l" state="o" />
    <connection from="BA2B" to="B2BA" fromLane="1" toLane="2" via=":B_4_0" tl="B" linkIndex="4" dir="t" state="o" />
    <connection from="BB2B" to="B2BA" fromLane="0" toLane="0" via=":B_5_0" tl="B" linkIndex="5" dir="r" state="O" />
    <connection from="BB2B" to="B2TL" fromLane="0" toLane="0" via=":B_6_0" tl="B" linkIndex="6" dir="s" state="O" />
    <connection from="BB2B" to="B2TL" fromLane="1" toLane="1" via=":B_6_1" tl="B" linkIndex="7" dir="s" state="O" />
    <connection from="BB2B" to="B2BC" fromLane="1" toLane="2" via=":B_8_0" tl="B" linkIndex="8" dir="l" state="o" />
    <connection from="BB2B" to="B2BB" fromLane="1" toLane="2" via=":B_9_0" tl="B" linkIndex="9" dir="t" state="o" />
    <connection from="BC2B" to="B2BB" fromLane="0" toLane="0" via=":B_10_0" tl="B" linkIndex="10" dir="r" state="o" />
    <connection from="BC2B" to="B2BA" fromLane="0" toLane="1" via=":B_11_0" tl="B" linkIndex="11" dir="s" state="o" />
    <connection from="BC2B" to="B2BA" fromLane="1" toLane="2" via=":B_11_1" tl="B" linkIndex="12" dir="s" state="o" />
    <connection from="BC2B" to="B2TL" fromLane="1" toLane="1" via=":B_13_0" tl="B" linkIndex="13" dir="l" state="o" />
    <connection from="BC2B" to="B2BC" fromLane="1" toLane="2" via=":B_14_0" tl="B" linkIndex="14" dir="t" state="o" />
    <connection from="C2CA" to="CA2C" fromLane="0" toLane="0" via=":CA_0_0" tl="CA" linkIndex="0" dir="t" state="O" />
    <connection from="C2CB" to="CB2C" fromLane="0" toLane="0" via=":CB_0_0" tl="CB" linkIndex="0" dir="t" state="O" />
    <connection from="C2CC" to="CC2C" fromLane="0" toLane="0" via=":CC_0_0" tl="CC" linkIndex="0" dir="t" state="O" />
    <connection from="C2TL" to="TL2B" fromLane="0" toLane="0" via=":TL_4_0" tl="TL" linkIndex="4" dir="r" state="o" />
    <connection from="C2TL" to="TL2A" fromLane="0" toLane="0" via=":TL_5_0" tl="TL" linkIndex="5" dir="s" state="o" />
    <connection from="CA2C" to="C2TL" fromLane="0" toLane="0" via=":C_4_0" tl="C" linkIndex="4" dir="r" state="o" />
    <connection from="CA2C" to="C2CC" fromLane="0" toLane="0" via=":C_5_0" tl="C" linkIndex="5" dir="s" state="o" />
    <connection from="CA2C" to="C2CB" fromLane="0" toLane="0" via=":C_6_0" tl="C" linkIndex="6" dir="l" state="o" />
    <connection from="CA2C" to="C2CA" fromLane="0" toLane="0" via=":C_7_0" tl="C" linkIndex="7" dir="t" state="o" />
    <connection from="CB2C" to="C2CA" fromLane="0" toLane="0" via=":C_8_0" tl="C" linkIndex="8" dir="r" state="O" />
    <connection from="CB2C" to="C2TL" fromLane="0" toLane="0" via=":C_9_0" tl="C" linkIndex="9" dir="s" state="O" />
    <connection from="CB2C" to="C2CC" fromLane="0" toLane="0" via=":C_10_0" tl="C" linkIndex="10" dir="l" state="o" />
    <connection from="CB2C" to="C2CB" fromLane="0" toLane="0" via=":C_11_0" tl="C" linkIndex="11" dir="t" state="o" />
    <connection from="CC2C" to="C2CB" fromLane="0" toLane="0" via=":C_12_0" tl="C" linkIndex="12" dir="r" state="o" />
    <connection from="CC2C" to="C2CA" fromLane="0" toLane="0" via=":C_13_0" tl="C" linkIndex="13" dir="s" state="o" />
    <connection from="CC2C" to="C2TL" fromLane="0" toLane="0" via=":C_14_0" tl="C" linkIndex="14" dir="l" state="o" />
    <connection from="CC2C" to="C2CC" fromLane="0" toLane="0" via=":C_15_0" tl="C" linkIndex="15" dir="t" state="o" />
    <connection from="D2DA" to="DA2D" fromLane="1" toLane="2" via=":DA_0_0" tl="DA" linkIndex="0" dir="t" state="O" />
    <connection from="D2DB" to="DB2D" fromLane="1" toLane="2" via=":DB_0_0" tl="DB" linkIndex="0" dir="t" state="O" />
    <connection from="D2DC" to="DC2D" fromLane="1" toLane="2" via=":DC_0_0" tl="DC" linkIndex="0" dir="t" state="O" />
    <connection from="D2TL" to="TL2C" fromLane="0" toLane="0" via=":TL_6_0" tl="TL" linkIndex="6" dir="r" state="O" />
    <connection from="D2TL" to="TL2B" fromLane="0" toLane="0" via=":TL_7_0" tl="TL" linkIndex="7" dir="s" state="O" />
    <connection from="D2TL" to="TL2B" fromLane="1" toLane="1" via=":TL_7_1" tl="TL" linkIndex="8" dir="s" state="O" />
    <connection from="D2TL" to="TL2A" fromLane="2" toLane="0" via=":TL_9_0" tl="TL" linkIndex="9" dir="l" state="o" />
    <connection from="DA2D" to="D2TL" fromLane="0" toLane="0" via=":D_10_0" tl="D" linkIndex="10" dir="r" state="O" />
    <connection from="DA2D" to="D2DC" fromLane="0" toLane="0" via=":D_11_0" tl="D" linkIndex="11" dir="s" state="O" />
    <connection from="DA2D" to="D2DC" fromLane="1" toLane="1" via=":D_11_1" tl="D" linkIndex="12" dir="s" state="O" />
    <connection from="DA2D" to="D2DB" fromLane="2" toLane="1" via=":D_13_0" tl="D" linkIndex="13" dir="l" state="o" />
    <connection from="DA2D" to="D2DA" fromLane="2" toLane="1" via=":D_14_0" tl="D" linkIndex="14" dir="t" state="o" />
    <connection from="DB2D" to="D2DA" fromLane="0" toLane="0" via=":D_15_0" tl="D" linkIndex="15" dir="r" state="o" />
    <connection from="DB2D" to="D2TL" fromLane="0" toLane="0" via=":D_16_0" tl="D" linkIndex="16" dir="s" state="o" />
    <connection from="DB2D" to="D2TL" fromLane="1" toLane="1" via=":D_16_1" tl="D" linkIndex="17" dir="s" state="o" />
    <connection from="DB2D" to="D2TL" fromLane="2" toLane="2" via=":D_16_2" tl="D" linkIndex="18" dir="s" state="o" />
    <connection from="DB2D" to="D2DC" fromLane="2" toLane="1" via=":D_19_0" tl="D" linkIndex="19" dir="l" state="o" />
    <connection from="DB2D" to="D2DB" fromLane="2" toLane="1" via=":D_20_0" tl="D" linkIndex="20" dir="t" state="o" />
    <connection from="DC2D" to="D2DB" fromLane="0" toLane="0" via=":D_0_0" tl="D" linkIndex="0" dir="r" state="O" />
    <connection from="DC2D" to="D2DA" fromLane="0" toLane="0" via=":D_1_0" tl="D" linkIndex="1" dir="s" state="O" />
    <connection from="DC2D" to="D2DA" fromLane="1" toLane="1" via=":D_1_1" tl="D" linkIndex="2" dir="s" state="O" />
    <connection from="DC2D" to="D2TL" fromLane="2" toLane="2" via=":D_3_0" tl="D" linkIndex="3" dir="l" state="o" />
    <connection from="DC2D" to="D2DC" fromLane="2" toLane="1" via=":D_4_0" tl="D" linkIndex="4" dir="t" state="o" />
    <connection from="TL2A" to="A2AC" fromLane="0" toLane="0" via=":A_0_0" tl="A" linkIndex="0" dir="r" state="O" />
    <connection from="TL2A" to="A2AB" fromLane="0" toLane="0" via=":A_1_0" tl="A" linkIndex="1" dir="s" state="O" />
    <connection from="TL2A" to="A2AA" fromLane="0" toLane="0" via=":A_2_0" tl="A" linkIndex="2" dir="l" state="O" />
    <connection from="TL2B" to="B2BC" fromLane="0" toLane="0" via=":B_15_0" tl="B" linkIndex="15" dir="r" state="O" />
    <connection from="TL2B" to="B2BB" fromLane="0" toLane="0" via=":B_16_0" tl="B" linkIndex="16" dir="s" state="O" />
    <connection from="TL2B" to="B2BB" fromLane="1" toLane="1" via=":B_16_1" tl="B" linkIndex="17" dir="s" state="O" />
    <connection from="TL2B" to="B2BB" fromLane="2" toLane="2" via=":B_16_2" tl="B" linkIndex="18" dir="s" state="O" />
    <connection from="TL2B" to="B2BA" fromLane="2" toLane="2" via=":B_19_0" tl="B" linkIndex="19" dir="l" state="o" />
    <connection from="TL2B" to="B2TL" fromLane="2" toLane="1" via=":B_20_0" tl="B" linkIndex="20" dir="t" state="o" />
    <connection from="TL2C" to="C2CC" fromLane="0" toLane="0" via=":C_0_0" tl="C" linkIndex="0" dir="r" state="O" />
    <connection from="TL2C" to="C2CB" fromLane="0" toLane="0" via=":C_1_0" tl="C" linkIndex="1" dir="s" state="O" />
    <connection from="TL2C" to="C2CA" fromLane="0" toLane="0" via=":C_2_0" tl="C" linkIndex="2" dir="l" state="o" />
    <connection from="TL2C" to="C2TL" fromLane="0" toLane="0" via=":C_3_0" tl="C" linkIndex="3" dir="t" state="o" />
    <connection from="TL2D" to="D2DC" fromLane="0" toLane="0" via=":D_5_0" tl="D" linkIndex="5" dir="r" state="o" />
    <connection from="TL2D" to="D2DB" fromLane="0" toLane="0" via=":D_6_0" tl="D" linkIndex="6" dir="s" state="o" />
    <connection from="TL2D" to="D2DB" fromLane="1" toLane="1" via=":D_6_1" tl="D" linkIndex="7" dir="s" state="o" />
    <connection from="TL2D" to="D2DA" fromLane="1" toLane="1" via=":D_8_0" tl="D" linkIndex="8" dir="l" state="o" />
    <connection from="TL2D" to="D2TL" fromLane="1" toLane="2" via=":D_9_0" tl="D" linkIndex="9" dir="t" state="o" />

    <connection from=":A_0" to="A2AC" fromLane="0" toLane="0" dir="r" state="M" />
    <connection from=":A_1" to="A2AB" fromLane="0" toLane="0" dir="s" state="M" />
    <connection from=":A_2" to="A2AA" fromLane="0" toLane="0" dir="l" state="M" />
    <connection from=":B_0" to="B2TL" fromLane="0" toLane="0" dir="r" state="M" />
    <connection from=":B_1" to="B2BC" fromLane="0" toLane="1" dir="s" state="M" />
    <connection from=":B_1" to="B2BC" fromLane="1" toLane="2" dir="s" state="M" />
    <connection from=":B_3" to="B2BB" fromLane="0" toLane="2" via=":B_21_0" dir="l" state="m" />
    <connection from=":B_21" to="B2BB" fromLane="0" toLane="2" dir="l" state="M" />
    <connection from=":B_4" to="B2BA" fromLane="0" toLane="2" via=":B_22_0" dir="t" state="m" />
    <connection from=":B_22" to="B2BA" fromLane="0" toLane="2" dir="t" state="M" />
    <connection from=":B_5" to="B2BA" fromLane="0" toLane="0" dir="r" state="M" />
    <connection from=":B_6" to="B2TL" fromLane="0" toLane="0" dir="s" state="M" />
    <connection from=":B_6" to="B2TL" fromLane="1" toLane="1" dir="s" state="M" />
    <connection from=":B_8" to="B2BC" fromLane="0" toLane="2" via=":B_23_0" dir="l" state="m" />
    <connection from=":B_23" to="B2BC" fromLane="0" toLane="2" dir="l" state="M" />
    <connection from=":B_9" to="B2BB" fromLane="0" toLane="2" via=":B_24_0" dir="t" state="m" />
    <connection from=":B_24" to="B2BB" fromLane="0" toLane="2" dir="t" state="M" />
    <connection from=":B_10" to="B2BB" fromLane="0" toLane="0" dir="r" state="M" />
    <connection from=":B_11" to="B2BA" fromLane="0" toLane="1" dir="s" state="M" />
    <connection from=":B_11" to="B2BA" fromLane="1" toLane="2" dir="s" state="M" />
    <connection from=":B_13" to="B2TL" fromLane="0" toLane="1" via=":B_25_0" dir="l" state="m" />
    <connection from=":B_25" to="B2TL" fromLane="0" toLane="1" dir="l" state="M" />
    <connection from=":B_14" to="B2BC" fromLane="0" toLane="2" via=":B_26_0" dir="t" state="m" />
    <connection from=":B_26" to="B2BC" fromLane="0" toLane="2" dir="t" state="M" />
    <connection from=":B_15" to="B2BC" fromLane="0" toLane="0" dir="r" state="M" />
    <connection from=":B_16" to="B2BB" fromLane="0" toLane="0" dir="s" state="M" />
    <connection from=":B_16" to="B2BB" fromLane="1" toLane="1" dir="s" state="M" />
    <connection from=":B_16" to="B2BB" fromLane="2" toLane="2" dir="s" state="M" />
    <connection from=":B_19" to="B2BA" fromLane="0" toLane="2" via=":B_27_0" dir="l" state="m" />
    <connection from=":B_27" to="B2BA" fromLane="0" toLane="2" dir="l" state="M" />
    <connection from=":B_20" to="B2TL" fromLane="0" toLane="1" via=":B_28_0" dir="t" state="m" />
    <connection from=":B_28" to="B2TL" fromLane="0" toLane="1" dir="t" state="M" />
    <connection from=":BA_0" to="BA2B" fromLane="0" toLane="1" dir="t" state="M" />
    <connection from=":BB_0" to="BB2B" fromLane="0" toLane="1" dir="t" state="M" />
    <connection from=":BC_0" to="BC2B" fromLane="0" toLane="1" dir="t" state="M" />
    <connection from=":B_intern_0" to="B2TL_intern" fromLane="0" toLane="0" dir="s" state="M" />
    <connection from=":B_intern_0" to="B2TL_intern" fromLane="1" toLane="1" dir="s" state="M" />
    <connection from=":B_intern_0" to="B2TL_intern" fromLane="2" toLane="2" dir="s" state="M" />
    <connection from=":C_0" to="C2CC" fromLane="0" toLane="0" dir="r" state="M" />
    <connection from=":C_1" to="C2CB" fromLane="0" toLane="0" dir="s" state="M" />
    <connection from=":C_2" to="C2CA" fromLane="0" toLane="0" via=":C_16_0" dir="l" state="m" />
    <connection from=":C_16" to="C2CA" fromLane="0" toLane="0" dir="l" state="M" />
    <connection from=":C_3" to="C2TL" fromLane="0" toLane="0" via=":C_17_0" dir="t" state="m" />
    <connection from=":C_17" to="C2TL" fromLane="0" toLane="0" dir="t" state="M" />
    <connection from=":C_4" to="C2TL" fromLane="0" toLane="0" dir="r" state="M" />
    <connection from=":C_5" to="C2CC" fromLane="0" toLane="0" dir="s" state="M" />
    <connection from=":C_6" to="C2CB" fromLane="0" toLane="0" via=":C_18_0" dir="l" state="m" />
    <connection from=":C_18" to="C2CB" fromLane="0" toLane="0" dir="l" state="M" />
    <connection from=":C_7" to="C2CA" fromLane="0" toLane="0" via=":C_19_0" dir="t" state="m" />
    <connection from=":C_19" to="C2CA" fromLane="0" toLane="0" dir="t" state="M" />
    <connection from=":C_8" to="C2CA" fromLane="0" toLane="0" dir="r" state="M" />
    <connection from=":C_9" to="C2TL" fromLane="0" toLane="0" dir="s" state="M" />
    <connection from=":C_10" to="C2CC" fromLane="0" toLane="0" via=":C_20_0" dir="l" state="m" />
    <connection from=":C_20" to="C2CC" fromLane="0" toLane="0" dir="l" state="M" />
    <connection from=":C_11" to="C2CB" fromLane="0" toLane="0" via=":C_21_0" dir="t" state="m" />
    <connection from=":C_21" to="C2CB" fromLane="0" toLane="0" dir="t" state="M" />
    <connection from=":C_12" to="C2CB" fromLane="0" toLane="0" dir="r" state="M" />
    <connection from=":C_13" to="C2CA" fromLane="0" toLane="0" dir="s" state="M" />
    <connection from=":C_14" to="C2TL" fromLane="0" toLane="0" via=":C_22_0" dir="l" state="m" />
    <connection from=":C_22" to="C2TL" fromLane="0" toLane="0" dir="l" state="M" />
    <connection from=":C_15" to="C2CC" fromLane="0" toLane="0" via=":C_23_0" dir="t" state="m" />
    <connection from=":C_23" to="C2CC" fromLane="0" toLane="0" dir="t" state="M" />
    <connection from=":CA_0" to="CA2C" fromLane="0" toLane="0" dir="t" state="M" />
    <connection from=":CB_0" to="CB2C" fromLane="0" toLane="0" dir="t" state="M" />
    <connection from=":CC_0" to="CC2C" fromLane="0" toLane="0" dir="t" state="M" />
    <connection from=":D_0" to="D2DB" fromLane="0" toLane="0" dir="r" state="M" />
    <connection from=":D_1" to="D2DA" fromLane="0" toLane="0" dir="s" state="M" />
    <connection from=":D_1" to="D2DA" fromLane="1" toLane="1" dir="s" state="M" />
    <connection from=":D_3" to="D2TL" fromLane="0" toLane="2" via=":D_21_0" dir="l" state="m" />
    <connection from=":D_21" to="D2TL" fromLane="0" toLane="2" dir="l" state="M" />
    <connection from=":D_4" to="D2DC" fromLane="0" toLane="1" via=":D_22_0" dir="t" state="m" />
    <connection from=":D_22" to="D2DC" fromLane="0" toLane="1" dir="t" state="M" />
    <connection from=":D_5" to="D2DC" fromLane="0" toLane="0" dir="r" state="M" />
    <connection from=":D_6" to="D2DB" fromLane="0" toLane="0" dir="s" state="M" />
    <connection from=":D_6" to="D2DB" fromLane="1" toLane="1" dir="s" state="M" />
    <connection from=":D_8" to="D2DA" fromLane="0" toLane="1" via=":D_23_0" dir="l" state="m" />
    <connection from=":D_23" to="D2DA" fromLane="0" toLane="1" dir="l" state="M" />
    <connection from=":D_9" to="D2TL" fromLane="0" toLane="2" via=":D_24_0" dir="t" state="m" />
    <connection from=":D_24" to="D2TL" fromLane="0" toLane="2" dir="t" state="M" />
    <connection from=":D_10" to="D2TL" fromLane="0" toLane="0" dir="r" state="M" />
    <connection from=":D_11" to="D2DC" fromLane="0" toLane="0" dir="s" state="M" />
    <connection from=":D_11" to="D2DC" fromLane="1" toLane="1" dir="s" state="M" />
    <connection from=":D_13" to="D2DB" fromLane="0" toLane="1" via=":D_25_0" dir="l" state="m" />
    <connection from=":D_25" to="D2DB" fromLane="0" toLane="1" dir="l" state="M" />
    <connection from=":D_14" to="D2DA" fromLane="0" toLane="1" via=":D_26_0" dir="t" state="m" />
    <connection from=":D_26" to="D2DA" fromLane="0" toLane="1" dir="t" state="M" />
    <connection from=":D_15" to="D2DA" fromLane="0" toLane="0" dir="r" state="M" />
    <connection from=":D_16" to="D2TL" fromLane="0" toLane="0" dir="s" state="M" />
    <connection from=":D_16" to="D2TL" fromLane="1" toLane="1" dir="s" state="M" />
    <connection from=":D_16" to="D2TL" fromLane="2" toLane="2" dir="s" state="M" />
    <connection from=":D_19" to="D2DC" fromLane="0" toLane="1" via=":D_27_0" dir="l" state="m" />
    <connection from=":D_27" to="D2DC" fromLane="0" toLane="1" dir="l" state="M" />
    <connection from=":D_20" to="D2DB" fromLane="0" toLane="1" via=":D_28_0" dir="t" state="m" />
    <connection from=":D_28" to="D2DB" fromLane="0" toLane="1" dir="t" state="M" />
    <connection from=":DA_0" to="DA2D" fromLane="0" toLane="2" dir="t" state="M" />
    <connection from=":DB_0" to="DB2D" fromLane="0" toLane="2" dir="t" state="M" />
    <connection from=":DC_0" to="DC2D" fromLane="0" toLane="2" dir="t" state="M" />
    <connection from=":TL_0" to="TL2A" fromLane="0" toLane="0" dir="r" state="M" />
    <connection from=":TL_1" to="TL2D" fromLane="0" toLane="0" dir="s" state="M" />
    <connection from=":TL_1" to="TL2D" fromLane="1" toLane="1" dir="s" state="M" />
    <connection from=":TL_3" to="TL2C" fromLane="0" toLane="0" via=":TL_10_0" dir="l" state="m" />
    <connection from=":TL_10" to="TL2C" fromLane="0" toLane="0" dir="l" state="M" />
    <connection from=":TL_4" to="TL2B" fromLane="0" toLane="0" dir="r" state="M" />
    <connection from=":TL_5" to="TL2A" fromLane="0" toLane="0" dir="s" state="M" />
    <connection from=":TL_6" to="TL2C" fromLane="0" toLane="0" dir="r" state="M" />
    <connection from=":TL_7" to="TL2B" fromLane="0" toLane="0" dir="s" state="M" />
    <connection from=":TL_7" to="TL2B" fromLane="1" toLane="1" dir="s" state="M" />
    <connection from=":TL_9" to="TL2A" fromLane="0" toLane="0" via=":TL_11_0" dir="l" state="m" />
    <connection from=":TL_11" to="TL2A" fromLane="0" toLane="0" dir="l" state="M" />

</net>